dijkies/__init__.py
dijkies/constants.py
dijkies/data_pipeline.py
dijkies/deployment.py
dijkies/entities.py
dijkies/exceptions.py
dijkies/exchange_market_api.py
dijkies/executors.py
dijkies/interfaces.py
dijkies/performance.py
dijkies-0.1.9.dist-info/WHEEL
dijkies-0.1.9.dist-info/METADATA
dijkies-0.1.9.dist-info/RECORD
