Metadata-Version: 2.3
Name: dijkies
Version: 0.1.9
Summary: A python framework that can be used to create, test and deploy trading algorithms.
Author: Arnold Dijk
Author-email: Arnold Dijk <arnold.dijk@teamrockstars.nl>
License: MIT
Requires-Dist: pandas>=2.3.3
Requires-Dist: pydantic>=2.12.5
Requires-Dist: python-binance>=1.0.33
Requires-Dist: python-bitvavo-api>=1.4.3
Requires-Python: >=3.11
Project-URL: Homepage, https://github.com/ArnoldDijk/dijkies
Project-URL: Source, https://github.com/ArnoldDijk/dijkies
Project-URL: Issues, https://github.com/ArnoldDijk/dijkies/issues
Project-URL: Documentation, https://github.com/ArnoldDijk/dijkies/blob/dev/README.md
